{
  "metadata": {
    "fecha_backup": "2025-11-11T20:56:15.179Z",
    "total_registros": 42,
    "version": "1.0",
    "sistema": "Open House Winston Churchill"
  },
  "inscripciones": [
    {
      "id": "ceaa9a41-d526-4e80-8ba7-9a9f2e327317",
      "nombre_aspirante": "Iris Giselle Martínez Gutiérrez",
      "nivel_academico": "primaria",
      "grado_escolar": "1primaria",
      "fecha_nacimiento": "2020-05-13",
      "nombre_padre": "María Teresa Gutiérrez Pérez",
      "nombre_madre": "María Teresa Gutiérrez Pérez",
      "telefono": "8331652499",
      "email": "tere.gtz10@outlook.com",
      "direccion": "N/A",
      "created_at": "2025-11-11T00:57:00.797814+00:00",
      "fecha_inscripcion": "2025-11-11T00:57:00.485+00:00",
      "updated_at": "2025-11-11T20:15:41.973183+00:00",
      "reminder_sent": false,
      "reminder_scheduled_for": "2025-12-05T00:00:00+00:00",
      "reminder_sent_at": null,
      "confirmacion_asistencia": "pendiente",
      "fecha_confirmacion": null
    },
    {
      "id": "ae2f177c-40d9-46fa-88ae-a4f8074a2901",
      "nombre_aspirante": "Renata Abigail Gutiérrez Castillo ",
      "nivel_academico": "primaria",
      "grado_escolar": "4primaria",
      "fecha_nacimiento": "2017-06-16",
      "nombre_padre": "Kathia Castillo Arcos ",
      "nombre_madre": "Kathia Castillo Arcos ",
      "telefono": "8333032842",
      "email": "kathiaarcos77@gmail.com",
      "direccion": "N/A",
      "created_at": "2025-11-11T00:49:07.960668+00:00",
      "fecha_inscripcion": "2025-11-11T00:49:07.844+00:00",
      "updated_at": "2025-11-11T20:15:41.973183+00:00",
      "reminder_sent": false,
      "reminder_scheduled_for": "2025-12-05T00:00:00+00:00",
      "reminder_sent_at": null,
      "confirmacion_asistencia": "pendiente",
      "fecha_confirmacion": null
    },
    {
      "id": "ee02a13d-32eb-46b1-b59b-f6cefc224f92",
      "nombre_aspirante": "Carlos Ricardo Vargas Delfín ",
      "nivel_academico": "secundaria",
      "grado_escolar": "7secundaria",
      "fecha_nacimiento": "2014-08-08",
      "nombre_padre": "Karla Odette Delfín Ferral ",
      "nombre_madre": "Karla Odette Delfín Ferral ",
      "telefono": "55 6801 7042",
      "email": "odette.delfin@gmail.com",
      "direccion": "N/A",
      "created_at": "2025-11-10T17:53:26.612632+00:00",
      "fecha_inscripcion": "2025-11-10T17:53:26.527+00:00",
      "updated_at": "2025-11-11T20:44:14.359654+00:00",
      "reminder_sent": false,
      "reminder_scheduled_for": "2025-12-05T00:00:00+00:00",
      "reminder_sent_at": null,
      "confirmacion_asistencia": "pendiente",
      "fecha_confirmacion": null
    },
    {
      "id": "4448cc61-b749-4cbb-a1d2-aecaa27c78e7",
      "nombre_aspirante": "Elías Benítez del Angel",
      "nivel_academico": "secundaria",
      "grado_escolar": "7secundaria",
      "fecha_nacimiento": "2014-04-09",
      "nombre_padre": "Angelica Del Angel ",
      "nombre_madre": "Angelica Del Angel ",
      "telefono": "8331468110",
      "email": "angelica.delangel@live.com.mx",
      "direccion": "N/A",
      "created_at": "2025-11-10T16:35:20.605894+00:00",
      "fecha_inscripcion": "2025-11-10T16:35:20.474+00:00",
      "updated_at": "2025-11-11T20:44:14.359654+00:00",
      "reminder_sent": false,
      "reminder_scheduled_for": "2025-12-05T00:00:00+00:00",
      "reminder_sent_at": null,
      "confirmacion_asistencia": "pendiente",
      "fecha_confirmacion": null
    },
    {
      "id": "a793c29b-cbfe-4c03-89d1-c8f65dc6fd38",
      "nombre_aspirante": "Ethan Cervantes vazquez",
      "nivel_academico": "secundaria",
      "grado_escolar": "7secundaria",
      "fecha_nacimiento": "2014-08-28",
      "nombre_padre": "Alejandro Cervantes espinoza",
      "nombre_madre": "Alejandro Cervantes espinoza",
      "telefono": "8331401006",
      "email": "eithan13@hotmail.com",
      "direccion": "N/A",
      "created_at": "2025-11-10T16:28:02.365921+00:00",
      "fecha_inscripcion": "2025-11-10T16:28:02.254+00:00",
      "updated_at": "2025-11-11T20:44:14.359654+00:00",
      "reminder_sent": false,
      "reminder_scheduled_for": "2025-12-05T00:00:00+00:00",
      "reminder_sent_at": null,
      "confirmacion_asistencia": "pendiente",
      "fecha_confirmacion": null
    },
    {
      "id": "f9cbed57-93b9-4f30-bfb1-007ee87b86d9",
      "nombre_aspirante": "Oliver Arturo Medina Moreno ",
      "nivel_academico": "primaria",
      "grado_escolar": "1primaria",
      "fecha_nacimiento": "2020-09-05",
      "nombre_padre": "Saori Gysel Moreno Gaspar ",
      "nombre_madre": "Saori Gysel Moreno Gaspar ",
      "telefono": "8332187568",
      "email": "saorimoreno@outlook.com",
      "direccion": "N/A",
      "created_at": "2025-11-10T16:11:35.395145+00:00",
      "fecha_inscripcion": "2025-11-10T16:11:35.325+00:00",
      "updated_at": "2025-11-11T20:15:41.973183+00:00",
      "reminder_sent": false,
      "reminder_scheduled_for": "2025-12-05T00:00:00+00:00",
      "reminder_sent_at": null,
      "confirmacion_asistencia": "pendiente",
      "fecha_confirmacion": null
    },
    {
      "id": "6318b930-a527-43cf-b8ef-94dd56243713",
      "nombre_aspirante": "Gerardo adrian Sánchez Rodríguez ",
      "nivel_academico": "primaria",
      "grado_escolar": "1primaria",
      "fecha_nacimiento": "2020-04-06",
      "nombre_padre": "Adriana Rodríguez Polanco ",
      "nombre_madre": "Adriana Rodríguez Polanco ",
      "telefono": "8332068880",
      "email": "ady.polanco05@gmail.com",
      "direccion": "N/A",
      "created_at": "2025-11-10T16:11:33.147011+00:00",
      "fecha_inscripcion": "2025-11-10T16:11:33.065+00:00",
      "updated_at": "2025-11-11T20:15:41.973183+00:00",
      "reminder_sent": false,
      "reminder_scheduled_for": "2025-12-05T00:00:00+00:00",
      "reminder_sent_at": null,
      "confirmacion_asistencia": "pendiente",
      "fecha_confirmacion": null
    },
    {
      "id": "b54e1d69-75d1-465c-a8b0-67551c03b90e",
      "nombre_aspirante": "Ema Larissa García Torres ",
      "nivel_academico": "primaria",
      "grado_escolar": "1primaria",
      "fecha_nacimiento": "2019-10-10",
      "nombre_padre": "Cindy Arianna Torres González ",
      "nombre_madre": "Cindy Arianna Torres González ",
      "telefono": "8331275596",
      "email": "gariannatorres@gmail.com",
      "direccion": "N/A",
      "created_at": "2025-11-10T16:09:56.988835+00:00",
      "fecha_inscripcion": "2025-11-10T16:09:56.868+00:00",
      "updated_at": "2025-11-11T20:15:41.973183+00:00",
      "reminder_sent": false,
      "reminder_scheduled_for": "2025-12-05T00:00:00+00:00",
      "reminder_sent_at": null,
      "confirmacion_asistencia": "pendiente",
      "fecha_confirmacion": null
    },
    {
      "id": "8b06b016-ecf8-4f85-863d-473b217f9c2d",
      "nombre_aspirante": "Luis Gerardo Cruz Serna ",
      "nivel_academico": "primaria",
      "grado_escolar": "1primaria",
      "fecha_nacimiento": "2020-07-31",
      "nombre_padre": "Arianna serna pando ",
      "nombre_madre": "Arianna serna pando ",
      "telefono": "8334625866",
      "email": "ariannasernap@gmail.com",
      "direccion": "N/A",
      "created_at": "2025-11-10T16:09:20.504442+00:00",
      "fecha_inscripcion": "2025-11-10T16:09:20.292+00:00",
      "updated_at": "2025-11-11T20:15:41.973183+00:00",
      "reminder_sent": false,
      "reminder_scheduled_for": "2025-12-05T00:00:00+00:00",
      "reminder_sent_at": null,
      "confirmacion_asistencia": "pendiente",
      "fecha_confirmacion": null
    },
    {
      "id": "2d597e49-e1b7-4f5b-b3ca-9eaa3f6e8f7a",
      "nombre_aspirante": "Enrique Emiliano Gijon Pedraza",
      "nivel_academico": "maternal",
      "grado_escolar": "maternalB",
      "fecha_nacimiento": "2023-04-27",
      "nombre_padre": "Ana Victoria Pedraza Zúñiga ",
      "nombre_madre": "Ana Victoria Pedraza Zúñiga ",
      "telefono": "8332809138",
      "email": "anapedraza2627@hotmail.com",
      "direccion": "N/A",
      "created_at": "2025-11-08T16:41:02.109827+00:00",
      "fecha_inscripcion": "2025-11-08T16:41:02.001+00:00",
      "updated_at": "2025-11-08T16:41:02.109827+00:00",
      "reminder_sent": false,
      "reminder_scheduled_for": "2025-11-28T00:00:00+00:00",
      "reminder_sent_at": null,
      "confirmacion_asistencia": "pendiente",
      "fecha_confirmacion": null
    },
    {
      "id": "50c24d16-c7b7-486b-bb42-a061c520ce81",
      "nombre_aspirante": "Ediani Rubi Castillo Maya ",
      "nivel_academico": "kinder",
      "grado_escolar": "kinder2",
      "fecha_nacimiento": "2022-05-20",
      "nombre_padre": "Salma Rubí Maya Cárdenas ",
      "nombre_madre": "Salma Rubí Maya Cárdenas ",
      "telefono": "8334759763",
      "email": "rubimayacardenas@gmail.com",
      "direccion": "N/A",
      "created_at": "2025-11-08T15:14:01.21232+00:00",
      "fecha_inscripcion": "2025-11-08T15:14:01.161+00:00",
      "updated_at": "2025-11-08T15:14:01.21232+00:00",
      "reminder_sent": false,
      "reminder_scheduled_for": "2025-11-28T00:00:00+00:00",
      "reminder_sent_at": null,
      "confirmacion_asistencia": "pendiente",
      "fecha_confirmacion": null
    },
    {
      "id": "7420feda-04ef-45ee-aed3-fb74008e77e6",
      "nombre_aspirante": "Álvaro Julián Pérez Maldonado",
      "nivel_academico": "primaria",
      "grado_escolar": "1primaria",
      "fecha_nacimiento": "2020-06-25",
      "nombre_padre": "Jessica Ainat Maldonado Garcia",
      "nombre_madre": "Jessica Ainat Maldonado Garcia",
      "telefono": "8333910126",
      "email": "jessicainatmg@gmail.com",
      "direccion": "N/A",
      "created_at": "2025-11-08T00:57:39.03057+00:00",
      "fecha_inscripcion": "2025-11-08T00:57:38.719+00:00",
      "updated_at": "2025-11-11T20:44:14.359654+00:00",
      "reminder_sent": false,
      "reminder_scheduled_for": "2025-12-05T00:00:00+00:00",
      "reminder_sent_at": null,
      "confirmacion_asistencia": "pendiente",
      "fecha_confirmacion": null
    },
    {
      "id": "39ca407d-ecf2-4587-b19c-12857cd741ef",
      "nombre_aspirante": "Natalia Ruiz Rustrián ",
      "nivel_academico": "primaria",
      "grado_escolar": "1primaria",
      "fecha_nacimiento": "2020-09-21",
      "nombre_padre": "Beatriz Rustrian ",
      "nombre_madre": "Beatriz Rustrian ",
      "telefono": "8332362985",
      "email": "betty_ruscer87@hotmail.com",
      "direccion": "N/A",
      "created_at": "2025-11-08T00:51:35.808823+00:00",
      "fecha_inscripcion": "2025-11-08T00:51:35.371+00:00",
      "updated_at": "2025-11-11T20:44:14.359654+00:00",
      "reminder_sent": false,
      "reminder_scheduled_for": "2025-12-05T00:00:00+00:00",
      "reminder_sent_at": null,
      "confirmacion_asistencia": "pendiente",
      "fecha_confirmacion": null
    },
    {
      "id": "cecd0f23-e2dc-4e6b-8c43-89529c498ae7",
      "nombre_aspirante": "Miguel Alejandro Rocha Wong",
      "nivel_academico": "secundaria",
      "grado_escolar": "7secundaria",
      "fecha_nacimiento": "2014-02-07",
      "nombre_padre": "Karen Larissa Wong Reyes",
      "nombre_madre": "Karen Larissa Wong Reyes",
      "telefono": "8332805009",
      "email": "marp47@hotmsil.com",
      "direccion": "N/A",
      "created_at": "2025-11-07T22:37:55.900435+00:00",
      "fecha_inscripcion": "2025-11-07T22:37:55.799+00:00",
      "updated_at": "2025-11-11T20:44:14.359654+00:00",
      "reminder_sent": false,
      "reminder_scheduled_for": "2025-12-05T00:00:00+00:00",
      "reminder_sent_at": null,
      "confirmacion_asistencia": "pendiente",
      "fecha_confirmacion": null
    },
    {
      "id": "ffe91b64-e62b-482b-97fd-5f94bda9fb46",
      "nombre_aspirante": "Roman Duque Castillo",
      "nivel_academico": "kinder",
      "grado_escolar": "kinder2",
      "fecha_nacimiento": "2022-09-18",
      "nombre_padre": "Lucero Duque Castillo",
      "nombre_madre": "Lucero Duque Castillo",
      "telefono": "8333110294",
      "email": "duquelucero237@gmail.com",
      "direccion": "N/A",
      "created_at": "2025-11-07T22:27:46.540774+00:00",
      "fecha_inscripcion": "2025-11-07T22:27:46.157+00:00",
      "updated_at": "2025-11-11T20:44:14.359654+00:00",
      "reminder_sent": false,
      "reminder_scheduled_for": "2025-11-28T00:00:00+00:00",
      "reminder_sent_at": null,
      "confirmacion_asistencia": "pendiente",
      "fecha_confirmacion": null
    },
    {
      "id": "d5364043-92e9-41fb-a7bf-89b6e8ba1ca6",
      "nombre_aspirante": "José Tadeo molar perez",
      "nivel_academico": "primaria",
      "grado_escolar": "1primaria",
      "fecha_nacimiento": "2020-02-26",
      "nombre_padre": "Isabel molar perez",
      "nombre_madre": "Isabel molar perez",
      "telefono": "4521126043",
      "email": "isabelmolarperez@gmail.com",
      "direccion": "N/A",
      "created_at": "2025-11-06T23:37:06.738617+00:00",
      "fecha_inscripcion": "2025-11-06T23:37:06.509+00:00",
      "updated_at": "2025-11-11T20:44:14.359654+00:00",
      "reminder_sent": false,
      "reminder_scheduled_for": "2025-12-05T00:00:00+00:00",
      "reminder_sent_at": null,
      "confirmacion_asistencia": "pendiente",
      "fecha_confirmacion": null
    },
    {
      "id": "0075c845-0c8a-434e-88b6-e887653c9c07",
      "nombre_aspirante": "Emilia Salazar Alejandro ",
      "nivel_academico": "primaria",
      "grado_escolar": "1primaria",
      "fecha_nacimiento": "2020-06-27",
      "nombre_padre": "Priscila Alejandro Meléndez ",
      "nombre_madre": "Priscila Alejandro Meléndez ",
      "telefono": "8334745928",
      "email": "melendez2708@outlook.com",
      "direccion": "N/A",
      "created_at": "2025-11-06T22:49:06.825302+00:00",
      "fecha_inscripcion": "2025-11-06T22:49:06.746+00:00",
      "updated_at": "2025-11-11T20:44:14.359654+00:00",
      "reminder_sent": false,
      "reminder_scheduled_for": "2025-12-05T00:00:00+00:00",
      "reminder_sent_at": null,
      "confirmacion_asistencia": "pendiente",
      "fecha_confirmacion": null
    },
    {
      "id": "a43717c0-9f08-4867-899f-dcb136f3bd15",
      "nombre_aspirante": "PAULINA MARTINEZ ALVA ",
      "nivel_academico": "primaria",
      "grado_escolar": "2primaria",
      "fecha_nacimiento": "2019-12-21",
      "nombre_padre": "Romina Alva Medina ",
      "nombre_madre": "Romina Alva Medina ",
      "telefono": "+528331477235",
      "email": "romina.alva1105@gmail.com",
      "direccion": "N/A",
      "created_at": "2025-11-06T17:48:17.616464+00:00",
      "fecha_inscripcion": "2025-11-06T17:48:17.23+00:00",
      "updated_at": "2025-11-11T20:44:14.359654+00:00",
      "reminder_sent": false,
      "reminder_scheduled_for": "2025-12-05T00:00:00+00:00",
      "reminder_sent_at": null,
      "confirmacion_asistencia": "pendiente",
      "fecha_confirmacion": null
    },
    {
      "id": "5c03e911-9912-4bc8-b0cb-1443160082d4",
      "nombre_aspirante": "Eleanor Obledo",
      "nivel_academico": "primaria",
      "grado_escolar": "1primaria",
      "fecha_nacimiento": "2020-11-25",
      "nombre_padre": "Jessica Torres Villebardet",
      "nombre_madre": "Jessica Torres Villebardet",
      "telefono": "8332347208",
      "email": "jessicaelizabeth012@gmail.com",
      "direccion": "N/A",
      "created_at": "2025-11-06T16:57:01.478711+00:00",
      "fecha_inscripcion": "2025-11-06T16:57:00.61+00:00",
      "updated_at": "2025-11-11T20:44:14.359654+00:00",
      "reminder_sent": false,
      "reminder_scheduled_for": "2025-12-05T00:00:00+00:00",
      "reminder_sent_at": null,
      "confirmacion_asistencia": "pendiente",
      "fecha_confirmacion": null
    },
    {
      "id": "c4c12fe4-0814-4f4d-b241-4f01967f6f76",
      "nombre_aspirante": "Jose rafael ramirez lopez",
      "nivel_academico": "kinder",
      "grado_escolar": "kinder3",
      "fecha_nacimiento": "2021-12-08",
      "nombre_padre": "Ana bassi lopez ramon ",
      "nombre_madre": "Ana bassi lopez ramon ",
      "telefono": "9711260956",
      "email": "ab_lr0990@hotmail.com",
      "direccion": "N/A",
      "created_at": "2025-11-06T14:52:46.430155+00:00",
      "fecha_inscripcion": "2025-11-06T14:52:46.23+00:00",
      "updated_at": "2025-11-11T20:44:14.359654+00:00",
      "reminder_sent": false,
      "reminder_scheduled_for": "2025-11-28T00:00:00+00:00",
      "reminder_sent_at": null,
      "confirmacion_asistencia": "pendiente",
      "fecha_confirmacion": null
    },
    {
      "id": "6c374c12-505b-4c4e-be31-2dbbb7ae8e62",
      "nombre_aspirante": "Ana Paula Ramírez López ",
      "nivel_academico": "primaria",
      "grado_escolar": "2primaria",
      "fecha_nacimiento": "2019-07-09",
      "nombre_padre": "Ana bassi lopez ramon ",
      "nombre_madre": "Ana bassi lopez ramon ",
      "telefono": "9711260956",
      "email": "ab_lr0990@hotmail.com",
      "direccion": "N/A",
      "created_at": "2025-11-06T14:51:41.300847+00:00",
      "fecha_inscripcion": "2025-11-06T14:51:40.483+00:00",
      "updated_at": "2025-11-11T20:44:14.359654+00:00",
      "reminder_sent": false,
      "reminder_scheduled_for": "2025-12-05T00:00:00+00:00",
      "reminder_sent_at": null,
      "confirmacion_asistencia": "pendiente",
      "fecha_confirmacion": null
    },
    {
      "id": "f17852e0-0d8b-4420-a70a-0c22aac10518",
      "nombre_aspirante": "Ruth Johanna Ruiz Cruz ",
      "nivel_academico": "primaria",
      "grado_escolar": "1primaria",
      "fecha_nacimiento": "2019-09-12",
      "nombre_padre": "Ruth Cruz ",
      "nombre_madre": "Ruth Cruz ",
      "telefono": "(833) 147-8747",
      "email": "ruthc591@gmail.com",
      "direccion": "N/A",
      "created_at": "2025-11-06T00:37:49.813928+00:00",
      "fecha_inscripcion": "2025-11-06T00:37:49.606+00:00",
      "updated_at": "2025-11-06T00:37:49.813928+00:00",
      "reminder_sent": false,
      "reminder_scheduled_for": "2025-12-05T00:00:00+00:00",
      "reminder_sent_at": null,
      "confirmacion_asistencia": "pendiente",
      "fecha_confirmacion": null
    },
    {
      "id": "15f20589-d6a2-4d9b-ac9a-b86e41be7de3",
      "nombre_aspirante": "Matteo Sebastián López Cervantes ",
      "nivel_academico": "kinder",
      "grado_escolar": "kinder2",
      "fecha_nacimiento": "2022-01-09",
      "nombre_padre": "Rosario Cervantes Martinez",
      "nombre_madre": "Rosario Cervantes Martinez",
      "telefono": "8332848149",
      "email": "rosscervantes3@gmail.com",
      "direccion": "N/A",
      "created_at": "2025-11-06T00:36:19.162868+00:00",
      "fecha_inscripcion": "2025-11-06T00:36:18.254+00:00",
      "updated_at": "2025-11-06T00:36:19.162868+00:00",
      "reminder_sent": false,
      "reminder_scheduled_for": "2025-11-28T00:00:00+00:00",
      "reminder_sent_at": null,
      "confirmacion_asistencia": "pendiente",
      "fecha_confirmacion": null
    },
    {
      "id": "2cec2652-ed54-43e3-9ab5-b789f5bd7ae4",
      "nombre_aspirante": "Maryellen Maldonado ",
      "nivel_academico": "maternal",
      "grado_escolar": "maternalA",
      "fecha_nacimiento": "2023-09-20",
      "nombre_padre": "Kimberly maldonado saldaña",
      "nombre_madre": "Kimberly maldonado saldaña",
      "telefono": "8335379525",
      "email": "makeupkm@outlook.com",
      "direccion": "N/A",
      "created_at": "2025-11-05T23:07:04.750209+00:00",
      "fecha_inscripcion": "2025-11-05T23:07:04.413+00:00",
      "updated_at": "2025-11-05T23:07:04.750209+00:00",
      "reminder_sent": false,
      "reminder_scheduled_for": "2025-11-28T00:00:00+00:00",
      "reminder_sent_at": null,
      "confirmacion_asistencia": "pendiente",
      "fecha_confirmacion": null
    },
    {
      "id": "c4fd3bf9-db1f-4789-9d75-e24d14b8c866",
      "nombre_aspirante": "Santiago Javier Angeles Gutiérrez ",
      "nivel_academico": "maternal",
      "grado_escolar": "maternalA",
      "fecha_nacimiento": "2024-08-05",
      "nombre_padre": "Bertha litzy Gutierrez Mendoza ",
      "nombre_madre": "Bertha litzy Gutierrez Mendoza ",
      "telefono": "8337468641",
      "email": "litzygutierrez0808@gmail.com",
      "direccion": "N/A",
      "created_at": "2025-11-05T22:58:17.956876+00:00",
      "fecha_inscripcion": "2025-11-05T22:58:17.302+00:00",
      "updated_at": "2025-11-05T22:58:17.956876+00:00",
      "reminder_sent": false,
      "reminder_scheduled_for": "2025-11-28T00:00:00+00:00",
      "reminder_sent_at": null,
      "confirmacion_asistencia": "pendiente",
      "fecha_confirmacion": null
    },
    {
      "id": "b307c485-3f18-4777-84d1-db055c259534",
      "nombre_aspirante": "Camila Sofía Martínez pimienta ",
      "nivel_academico": "maternal",
      "grado_escolar": "maternalA",
      "fecha_nacimiento": "2023-11-26",
      "nombre_padre": "Cinthia Guadalupe pimienta Salazar ",
      "nombre_madre": "Cinthia Guadalupe pimienta Salazar ",
      "telefono": "8331205155",
      "email": "cinpims@hotmail.com",
      "direccion": "N/A",
      "created_at": "2025-11-05T18:40:46.726374+00:00",
      "fecha_inscripcion": "2025-11-05T18:40:46.496+00:00",
      "updated_at": "2025-11-05T18:40:46.726374+00:00",
      "reminder_sent": false,
      "reminder_scheduled_for": "2025-11-28T00:00:00+00:00",
      "reminder_sent_at": null,
      "confirmacion_asistencia": "pendiente",
      "fecha_confirmacion": null
    },
    {
      "id": "7ce331cc-3be5-425b-8642-b76ed19df15f",
      "nombre_aspirante": "Kiara Yaiza Arozqueta Ramos ",
      "nivel_academico": "primaria",
      "grado_escolar": "4primaria",
      "fecha_nacimiento": "2017-10-06",
      "nombre_padre": "Emmy Alexcis Ramos Castro ",
      "nombre_madre": "Emmy Alexcis Ramos Castro ",
      "telefono": "8333259729",
      "email": "alex1812@hotmail.com",
      "direccion": "N/A",
      "created_at": "2025-11-03T15:01:23.563684+00:00",
      "fecha_inscripcion": "2025-11-03T15:01:22.585+00:00",
      "updated_at": "2025-11-03T15:01:23.563684+00:00",
      "reminder_sent": false,
      "reminder_scheduled_for": "2025-12-05T00:00:00+00:00",
      "reminder_sent_at": null,
      "confirmacion_asistencia": "pendiente",
      "fecha_confirmacion": null
    },
    {
      "id": "d1255fa1-33d2-4bcd-b2e0-e0b46fd14214",
      "nombre_aspirante": "Abdo Santiago Abud Vite ",
      "nivel_academico": "secundaria",
      "grado_escolar": "7secundaria",
      "fecha_nacimiento": "2014-05-10",
      "nombre_padre": "Sugey Luque Lara",
      "nombre_madre": "Sugey Luque Lara",
      "telefono": "8332555631",
      "email": "Sugey.luque29@gmail.com",
      "direccion": "N/A",
      "created_at": "2025-10-30T22:10:15.169338+00:00",
      "fecha_inscripcion": "2025-10-30T22:10:14.494+00:00",
      "updated_at": "2025-11-11T20:44:14.359654+00:00",
      "reminder_sent": false,
      "reminder_scheduled_for": "2025-12-05T00:00:00+00:00",
      "reminder_sent_at": null,
      "confirmacion_asistencia": "pendiente",
      "fecha_confirmacion": null
    },
    {
      "id": "c6bf2eeb-5074-4963-a0b0-a65cebee56cf",
      "nombre_aspirante": "Hannah Yasu Landeros Torrws",
      "nivel_academico": "secundaria",
      "grado_escolar": "7secundaria",
      "fecha_nacimiento": "2013-02-23",
      "nombre_padre": "Karen Berenice Landeros Torres",
      "nombre_madre": "Karen Berenice Landeros Torres",
      "telefono": "8332038025",
      "email": "blt230213@icloud.com",
      "direccion": "N/A",
      "created_at": "2025-10-30T17:55:51.277657+00:00",
      "fecha_inscripcion": "2025-10-30T17:55:50.929+00:00",
      "updated_at": "2025-11-11T20:44:14.359654+00:00",
      "reminder_sent": false,
      "reminder_scheduled_for": "2025-12-05T00:00:00+00:00",
      "reminder_sent_at": null,
      "confirmacion_asistencia": "pendiente",
      "fecha_confirmacion": null
    },
    {
      "id": "5f326904-69c7-42ec-9e92-38d2458d3fcd",
      "nombre_aspirante": "Kiara Yaiza Arozqueta Ramos ",
      "nivel_academico": "primaria",
      "grado_escolar": "4primaria",
      "fecha_nacimiento": "2017-10-06",
      "nombre_padre": "Emmy Alexcis Ramos Castro ",
      "nombre_madre": "Emmy Alexcis Ramos Castro ",
      "telefono": "8333259729",
      "email": "alex1812@hotmail.com",
      "direccion": "N/A",
      "created_at": "2025-10-29T18:05:15.837189+00:00",
      "fecha_inscripcion": "2025-10-29T18:05:15.561+00:00",
      "updated_at": "2025-11-11T20:44:14.359654+00:00",
      "reminder_sent": false,
      "reminder_scheduled_for": "2025-12-05T00:00:00+00:00",
      "reminder_sent_at": null,
      "confirmacion_asistencia": "pendiente",
      "fecha_confirmacion": null
    },
    {
      "id": "f424f32d-a69f-4db4-a2b6-b3a86b30ccbc",
      "nombre_aspirante": "JAVIER RAFAEL VAZQUEZ MARTINEZ",
      "nivel_academico": "secundaria",
      "grado_escolar": "7secundaria",
      "fecha_nacimiento": "2014-04-07",
      "nombre_padre": "NANCY ELENA MARTINEZ HERNANDEZ",
      "nombre_madre": "NANCY ELENA MARTINEZ HERNANDEZ",
      "telefono": "8331557677",
      "email": "cp.nancy@hotmail.com",
      "direccion": "N/A",
      "created_at": "2025-10-28T00:13:08.902747+00:00",
      "fecha_inscripcion": "2025-10-28T00:13:08.65+00:00",
      "updated_at": "2025-11-11T20:44:14.359654+00:00",
      "reminder_sent": false,
      "reminder_scheduled_for": "2025-12-05T00:00:00+00:00",
      "reminder_sent_at": null,
      "confirmacion_asistencia": "pendiente",
      "fecha_confirmacion": null
    },
    {
      "id": "0de05d5c-fcca-40a7-885b-ddbd98fb3dbf",
      "nombre_aspirante": "HECTOR EVARISTO ENRIQUEZ MARTINEZ",
      "nivel_academico": "primaria",
      "grado_escolar": "1primaria",
      "fecha_nacimiento": "2020-10-06",
      "nombre_padre": "EVARISTO ENRIQUEZ REYNA",
      "nombre_madre": "EVARISTO ENRIQUEZ REYNA",
      "telefono": "8333435872",
      "email": "vari_ae92@hotmail.com",
      "direccion": "N/A",
      "created_at": "2025-10-28T00:11:55.737642+00:00",
      "fecha_inscripcion": "2025-10-28T00:11:54.953+00:00",
      "updated_at": "2025-11-11T20:44:14.359654+00:00",
      "reminder_sent": false,
      "reminder_scheduled_for": "2025-12-05T00:00:00+00:00",
      "reminder_sent_at": null,
      "confirmacion_asistencia": "pendiente",
      "fecha_confirmacion": null
    },
    {
      "id": "6aef4256-3eae-4c62-ab85-139c974f30ae",
      "nombre_aspirante": "Nerea Molina bielma ",
      "nivel_academico": "primaria",
      "grado_escolar": "1primaria",
      "fecha_nacimiento": "2020-09-10",
      "nombre_padre": "Chantal bielma ",
      "nombre_madre": "Chantal bielma ",
      "telefono": "8331200707",
      "email": "chantal_bb@hotmail.com",
      "direccion": "N/A",
      "created_at": "2025-10-27T21:59:11.584307+00:00",
      "fecha_inscripcion": "2025-10-27T21:59:10.873+00:00",
      "updated_at": "2025-11-11T20:44:14.359654+00:00",
      "reminder_sent": false,
      "reminder_scheduled_for": "2025-12-05T00:00:00+00:00",
      "reminder_sent_at": null,
      "confirmacion_asistencia": "pendiente",
      "fecha_confirmacion": null
    },
    {
      "id": "fe2e2883-7fd9-4b12-912e-dddd35ad6522",
      "nombre_aspirante": "Farid Berrones Sierra",
      "nivel_academico": "primaria",
      "grado_escolar": "1primaria",
      "fecha_nacimiento": "2020-03-11",
      "nombre_padre": "Abraham Berrones ",
      "nombre_madre": "Abraham Berrones ",
      "telefono": "8332461568",
      "email": "stephaniasierra89@hotmail.com",
      "direccion": "N/A",
      "created_at": "2025-10-24T21:42:49.070408+00:00",
      "fecha_inscripcion": "2025-10-24T21:42:48.267+00:00",
      "updated_at": "2025-10-24T21:42:49.070408+00:00",
      "reminder_sent": false,
      "reminder_scheduled_for": "2025-12-05T00:00:00+00:00",
      "reminder_sent_at": null,
      "confirmacion_asistencia": "pendiente",
      "fecha_confirmacion": null
    },
    {
      "id": "42441da9-4f57-497d-b15b-2e005cd27d6a",
      "nombre_aspirante": "Mathias Joaquín Juárez García ",
      "nivel_academico": "secundaria",
      "grado_escolar": "7secundaria",
      "fecha_nacimiento": "2014-12-04",
      "nombre_padre": "Mayra de Jesús García Chávez ",
      "nombre_madre": "Mayra de Jesús García Chávez ",
      "telefono": "8331605944",
      "email": "may.mathi.ary@gmail.com",
      "direccion": "N/A",
      "created_at": "2025-10-24T17:49:48.332746+00:00",
      "fecha_inscripcion": "2025-10-24T17:49:48.238+00:00",
      "updated_at": "2025-10-24T17:49:48.332746+00:00",
      "reminder_sent": false,
      "reminder_scheduled_for": "2025-12-05T00:00:00+00:00",
      "reminder_sent_at": null,
      "confirmacion_asistencia": "pendiente",
      "fecha_confirmacion": null
    },
    {
      "id": "1700be4f-41d1-4cce-9b80-e272e4e4f7e7",
      "nombre_aspirante": "JUAN CARLOS PRUEBA",
      "nivel_academico": "primaria",
      "grado_escolar": "1primaria",
      "fecha_nacimiento": "2025-10-03",
      "nombre_padre": "MARIO ALEJANDRO GALVAN ESCOBEDO",
      "nombre_madre": "MARIO ALEJANDRO GALVAN ESCOBEDO",
      "telefono": "8333246904",
      "email": "isc.escobedo@gmail.com",
      "direccion": "N/A",
      "created_at": "2025-10-24T17:35:21.084585+00:00",
      "fecha_inscripcion": "2025-10-24T17:35:20.727+00:00",
      "updated_at": "2025-10-29T19:06:58.326135+00:00",
      "reminder_sent": false,
      "reminder_scheduled_for": "2025-12-05T00:00:00+00:00",
      "reminder_sent_at": null,
      "confirmacion_asistencia": "confirmado",
      "fecha_confirmacion": "2025-10-29T19:06:58.304+00:00"
    },
    {
      "id": "240bb282-da8f-4b55-a39f-15376aed4363",
      "nombre_aspirante": "Jamie Michelle Cabrales Ruiz",
      "nivel_academico": "secundaria",
      "grado_escolar": "7secundaria",
      "fecha_nacimiento": "2014-09-17",
      "nombre_padre": "Alejandra Ruiz Narvaez",
      "nombre_madre": "Alejandra Ruiz Narvaez",
      "telefono": "8331570198",
      "email": "alex_parker16@hotmail.com",
      "direccion": "N/A",
      "created_at": "2025-10-23T23:30:10.868078+00:00",
      "fecha_inscripcion": "2025-10-23T23:30:10.091+00:00",
      "updated_at": "2025-11-11T20:37:13.515751+00:00",
      "reminder_sent": false,
      "reminder_scheduled_for": "2025-12-05T00:00:00+00:00",
      "reminder_sent_at": null,
      "confirmacion_asistencia": "pendiente",
      "fecha_confirmacion": null
    },
    {
      "id": "2fa5aa45-424b-48cb-8d3a-862903b611aa",
      "nombre_aspirante": "Yarandy virimar becerra macias",
      "nivel_academico": "secundaria",
      "grado_escolar": "7secundaria",
      "fecha_nacimiento": "2014-02-15",
      "nombre_padre": "Andrea viridiana macias hernandez ",
      "nombre_madre": "Andrea viridiana macias hernandez ",
      "telefono": "8334302748",
      "email": "andymacbec@gmail.com",
      "direccion": "N/A",
      "created_at": "2025-10-23T22:33:29.696364+00:00",
      "fecha_inscripcion": "2025-10-23T22:33:28.923+00:00",
      "updated_at": "2025-11-11T20:37:13.515751+00:00",
      "reminder_sent": false,
      "reminder_scheduled_for": "2025-12-05T00:00:00+00:00",
      "reminder_sent_at": null,
      "confirmacion_asistencia": "pendiente",
      "fecha_confirmacion": null
    },
    {
      "id": "581415db-3aa8-428a-baa0-37bb3e5a3163",
      "nombre_aspirante": "Jose Tadeo molar perez",
      "nivel_academico": "primaria",
      "grado_escolar": "1primaria",
      "fecha_nacimiento": "2020-02-26",
      "nombre_padre": "Isabel Molar perez",
      "nombre_madre": "Isabel Molar perez",
      "telefono": "4521126043",
      "email": "isabelmolarperez@gmail.com",
      "direccion": "N/A",
      "created_at": "2025-10-22T22:53:07.297768+00:00",
      "fecha_inscripcion": "2025-10-22T22:53:07.156+00:00",
      "updated_at": "2025-11-11T20:37:13.515751+00:00",
      "reminder_sent": false,
      "reminder_scheduled_for": "2025-12-05T00:00:00+00:00",
      "reminder_sent_at": null,
      "confirmacion_asistencia": "pendiente",
      "fecha_confirmacion": null
    },
    {
      "id": "0268c4b8-82e2-4e1a-8f03-df385c2c4ddb",
      "nombre_aspirante": "Jose Tadeo molar perez",
      "nivel_academico": "kinder",
      "grado_escolar": "kinder1",
      "fecha_nacimiento": "2020-02-26",
      "nombre_padre": "Isabel Molar perez",
      "nombre_madre": "Isabel Molar perez",
      "telefono": "4521126043",
      "email": "isabelmolarperez@gmail.com",
      "direccion": "N/A",
      "created_at": "2025-10-22T22:51:26.650927+00:00",
      "fecha_inscripcion": "2025-10-22T22:51:26.116+00:00",
      "updated_at": "2025-11-11T20:44:14.359654+00:00",
      "reminder_sent": false,
      "reminder_scheduled_for": "2025-11-28T00:00:00+00:00",
      "reminder_sent_at": null,
      "confirmacion_asistencia": "pendiente",
      "fecha_confirmacion": null
    },
    {
      "id": "cd7db032-e31b-45b0-adf5-d36317a455d5",
      "nombre_aspirante": "Hansel Leonardo Gamez Sánchez ",
      "nivel_academico": "primaria",
      "grado_escolar": "1primaria",
      "fecha_nacimiento": "2020-08-09",
      "nombre_padre": "Alma rocio Sánchez García ",
      "nombre_madre": "Alma rocio Sánchez García ",
      "telefono": "8332331242",
      "email": "almiuxx9923@gmail.com",
      "direccion": "N/A",
      "created_at": "2025-10-22T22:24:52.202828+00:00",
      "fecha_inscripcion": "2025-10-22T22:24:51.606+00:00",
      "updated_at": "2025-11-11T20:37:13.515751+00:00",
      "reminder_sent": false,
      "reminder_scheduled_for": "2025-12-05T00:00:00+00:00",
      "reminder_sent_at": null,
      "confirmacion_asistencia": "pendiente",
      "fecha_confirmacion": null
    },
    {
      "id": "36f62914-5a66-476b-8238-1021ec2dad23",
      "nombre_aspirante": "Cristian Yael Reyes Noriega ",
      "nivel_academico": "secundaria",
      "grado_escolar": "7secundaria",
      "fecha_nacimiento": "2014-05-30",
      "nombre_padre": "Yaneli Georgette Noriega Rebullosa ",
      "nombre_madre": "Yaneli Georgette Noriega Rebullosa ",
      "telefono": "8333223063",
      "email": "Santacruzlele@gmail.com",
      "direccion": "N/A",
      "created_at": "2025-10-21T23:13:23.615082+00:00",
      "fecha_inscripcion": "2025-10-21T23:13:23.032+00:00",
      "updated_at": "2025-11-11T20:37:13.515751+00:00",
      "reminder_sent": false,
      "reminder_scheduled_for": "2025-12-05T00:00:00+00:00",
      "reminder_sent_at": null,
      "confirmacion_asistencia": "pendiente",
      "fecha_confirmacion": null
    }
  ]
}